@(specialMentions: viewmodels.TADSpecialMention)
<fo:block>
    @if(specialMentions.additionalInfoCoded.description.trim.nonEmpty) {
        @if(specialMentions.additionalInfoCoded.description.trim.length > 6) {
            <fo:inline>Export </fo:inline>
            <fo:inline font-weight="bold">@specialMentions.valToInsert</fo:inline>
            <fo:inline>@specialMentions.additionalInfoCoded.description.split("Export", 2).last.trim</fo:inline>
            @if(specialMentions.specialMention.additionalInformation.exists(_.trim.nonEmpty)) {
                <fo:inline>-
                    @specialMentions.specialMention.additionalInformation
                </fo:inline>
            }
        } else {
            @specialMentions.additionalInfoCoded.description
        }
    } else {
        <fo:inline font-style="italic">@specialMentions.additionalInfoCoded.code</fo:inline>
        <fo:inline font-weight="bold"> @specialMentions.valToInsert</fo:inline>
        @specialMentions.specialMention.additionalInformation.map{ additionalInformation =>
            @if(additionalInformation.nonEmpty){
                <fo:inline>- @additionalInformation</fo:inline>
            }
        }
    }
</fo:block>